gridseal/__init__.py
gridseal/_version.py
gridseal/cli.py
gridseal/py.typed
gridseal/adapters/__init__.py
gridseal/adapters/base.py
gridseal/adapters/langfuse.py
gridseal/audit/__init__.py
gridseal/audit/integrity.py
gridseal/audit/store.py
gridseal/audit/backends/__init__.py
gridseal/audit/backends/base.py
gridseal/audit/backends/memory.py
gridseal/audit/backends/postgresql.py
gridseal/audit/backends/sqlite.py
gridseal/core/__init__.py
gridseal/core/config.py
gridseal/core/context.py
gridseal/core/exceptions.py
gridseal/core/types.py
gridseal/integrations/__init__.py
gridseal/integrations/langchain.py
gridseal/integrations/langfuse.py
gridseal/verification/__init__.py
gridseal/verification/claims.py
gridseal/verification/engine.py
gridseal/verification/nli.py
gridseal/verification/checks/__init__.py
gridseal/verification/checks/base.py
gridseal/verification/checks/citation.py
gridseal/verification/checks/confidence.py
gridseal/verification/checks/grounding.py
gridseal/verification/checks/relevance.py
gridseal-0.4.0.dist-info/METADATA
gridseal-0.4.0.dist-info/WHEEL
gridseal-0.4.0.dist-info/entry_points.txt
gridseal-0.4.0.dist-info/licenses/LICENSE
gridseal-0.4.0.dist-info/RECORD
